odoo/addons/shopfloor_batch_automatic_creation/README.rst
odoo/addons/shopfloor_batch_automatic_creation/__init__.py
odoo/addons/shopfloor_batch_automatic_creation/__manifest__.py
odoo/addons/shopfloor_batch_automatic_creation/actions/__init__.py
odoo/addons/shopfloor_batch_automatic_creation/actions/picking_batch_auto_create.py
odoo/addons/shopfloor_batch_automatic_creation/i18n/es_AR.po
odoo/addons/shopfloor_batch_automatic_creation/i18n/shopfloor_batch_automatic_creation.pot
odoo/addons/shopfloor_batch_automatic_creation/models/__init__.py
odoo/addons/shopfloor_batch_automatic_creation/models/shopfloor_menu.py
odoo/addons/shopfloor_batch_automatic_creation/readme/CONTRIBUTORS.rst
odoo/addons/shopfloor_batch_automatic_creation/readme/CREDITS.rst
odoo/addons/shopfloor_batch_automatic_creation/readme/DESCRIPTION.rst
odoo/addons/shopfloor_batch_automatic_creation/services/__init__.py
odoo/addons/shopfloor_batch_automatic_creation/services/cluster_picking.py
odoo/addons/shopfloor_batch_automatic_creation/static/description/icon.png
odoo/addons/shopfloor_batch_automatic_creation/static/description/index.html
odoo/addons/shopfloor_batch_automatic_creation/tests/__init__.py
odoo/addons/shopfloor_batch_automatic_creation/tests/test_batch_create.py
odoo/addons/shopfloor_batch_automatic_creation/views/shopfloor_menu_views.xml
odoo14_addon_shopfloor_batch_automatic_creation-14.0.1.2.0.dist-info/METADATA
odoo14_addon_shopfloor_batch_automatic_creation-14.0.1.2.0.dist-info/WHEEL
odoo14_addon_shopfloor_batch_automatic_creation-14.0.1.2.0.dist-info/top_level.txt
odoo14_addon_shopfloor_batch_automatic_creation-14.0.1.2.0.dist-info/RECORD
